{"assets":{"85BCA963944A71E6E88951D92BFE7D94":{"type":"texture","index":6,"assetRequest":{"type":"slide","state":"contents","slide":"none"},"url":{"native":"assets/F93187BD-B816-4D09-AF90-BDB65834A566.pdf"},"width":960,"height":540},"D1C3167F6F8B15101F23012D177C21C4":{"type":"texture","index":4,"assetRequest":{"type":"slide","state":"contents","slide":"none"},"url":{"native":"assets/F93187BD-B816-4D09-AF90-BDB65834A566.pdf"},"width":88,"height":88},"8090B41B8C80976C270CD97E8301335F":{"type":"texture","index":0,"assetRequest":{"type":"slide","state":"contents","slide":"none"},"url":{"native":"assets/F93187BD-B816-4D09-AF90-BDB65834A566.pdf"},"width":960,"height":540},"D9D638C947AE8DEEB09674AFD582DF6A":{"type":"texture","index":7,"assetRequest":{"type":"slide","state":"contents","slide":"none"},"url":{"native":"assets/F93187BD-B816-4D09-AF90-BDB65834A566.pdf"},"width":960,"height":540},"789EB8E7F504F944BCAF5FB827FDCF95":{"type":"texture","index":1,"assetRequest":{"type":"slide","state":"contents","slide":"none"},"url":{"native":"assets/F93187BD-B816-4D09-AF90-BDB65834A566.pdf"},"width":112,"height":30},"28BEA62E24033B5528476B7B1872C063":{"type":"texture","index":2,"assetRequest":{"type":"slide","state":"contents","slide":"none"},"url":{"native":"assets/F93187BD-B816-4D09-AF90-BDB65834A566.pdf"},"width":87,"height":87},"BA5196ECBF181D644F02D7CA74EA7770":{"type":"texture","index":3,"assetRequest":{"type":"slide","state":"contents","slide":"none"},"url":{"native":"assets/F93187BD-B816-4D09-AF90-BDB65834A566.pdf"},"width":785,"height":186},"CA4490732041C7B0251B62D01F9E94E8":{"type":"texture","index":5,"assetRequest":{"type":"slide","state":"contents","slide":"none"},"url":{"native":"assets/F93187BD-B816-4D09-AF90-BDB65834A566.pdf"},"width":88,"height":87}},"events":[{"effects":[{"beginTime":0,"baseLayer":{"animations":[],"initialState":{"affineTransform":[1,0,0,1,0,0],"masksToBounds":false,"rotation":0,"scale":1,"position":{"pointX":479.9999542236328,"pointY":153.3014946574592},"width":352.1852722167969,"sublayerTransform":[1,0,0,0,0,1,0,0,0,0,1,0,0,0,0,1],"contentsRect":{"y":0,"x":0,"width":1,"height":1},"opacity":1,"edgeAntialiasingMask":251658240,"height":47.37007915866843,"hidden":false,"anchorPoint":{"pointX":0.5,"pointY":0.5}},"objectID":"E7C0F144-AD3B-4153-9F82-968386AE8923","layers":[{"animations":[],"initialState":{"affineTransform":[1,0,0,1,0,0],"masksToBounds":false,"rotation":0,"scale":1,"position":{"pointX":176.0926818847656,"pointY":140.383544921875},"width":352.1852722167969,"sublayerTransform":[1,0,0,0,0,1,0,0,0,0,1,-0.0007001582493355197,0,0,0,1],"contentsRect":{"y":0,"x":0,"width":1,"height":1},"opacity":1,"edgeAntialiasingMask":251658240,"height":47.37007915866843,"hidden":false,"anchorPoint":{"pointX":0.5000001299780849,"pointY":2.963548877586912}},"layers":[{"animations":[{"timeOffset":0,"beginTime":1e-100,"repeatCount":0,"animations":[{"timeOffset":0,"from":{"scalar":0},"beginTime":0,"repeatCount":0,"fillMode":"both","duration":0.5,"autoreverses":false,"timingFunction":"EaseInEaseOut","property":"opacity","to":{"scalar":1}},{"timeOffset":0,"from":{"scalar":false},"beginTime":0,"repeatCount":0,"fillMode":"forwards","property":"hidden","autoreverses":false,"duration":0.5,"to":{"scalar":false}}],"fillMode":"both","autoreverses":false,"duration":0.5}],"layers":[],"texturedRectangle":{"singleTextureOpacity":1,"textXHeight":0.5600000000000001,"textBaseline":0.8260491689046224,"isBackgroundTexture":true,"isVerticalText":false,"textColor":[1,1,1,1],"textureType":6},"initialState":{"affineTransform":[1,0,0,1,0,0],"masksToBounds":false,"rotation":0,"scale":1,"position":{"pointX":60.09268188476562,"pointY":24.383544921875},"width":112,"sublayerTransform":[1,0,0,0,0,1,0,0,0,0,1,0,0,0,0,1],"contentsRect":{"y":0,"x":0,"width":1,"height":1},"opacity":1,"edgeAntialiasingMask":0,"height":30,"hidden":true,"anchorPoint":{"pointX":0.5,"pointY":0.5}},"texture":"789EB8E7F504F944BCAF5FB827FDCF95"}]}]},"effects":[],"duration":0.5,"type":"buildIn","attributes":{"direction":11},"name":"apple:wipe","objectID":"E7C0F144-AD3B-4153-9F82-968386AE8923"},{"beginTime":0,"baseLayer":{"animations":[],"initialState":{"affineTransform":[1,0,0,1,0,0],"masksToBounds":false,"rotation":0,"scale":1,"position":{"pointX":391.446195602417,"pointY":276.6713714599609},"width":84.49079861331063,"sublayerTransform":[1,0,0,0,0,1,0,0,0,0,1,0,0,0,0,1],"contentsRect":{"y":0,"x":0,"width":1,"height":1},"opacity":1,"edgeAntialiasingMask":251658240,"height":84.49079861331063,"hidden":false,"anchorPoint":{"pointX":0.5,"pointY":0.5}},"objectID":"EC17F182-85EA-4087-B397-F13CA2D275A2","layers":[{"animations":[],"initialState":{"affineTransform":[1,0,0,1,0,0],"masksToBounds":false,"rotation":0,"scale":1,"position":{"pointX":130.7992037042383,"pointY":35.57402784669438},"width":84.49079861331063,"sublayerTransform":[1,0,0,0,0,1,0,0,0,0,1,-0.0007001582493355197,0,0,0,1],"contentsRect":{"y":0,"x":0,"width":1,"height":1},"opacity":1,"edgeAntialiasingMask":251658240,"height":84.49079861331063,"hidden":false,"anchorPoint":{"pointX":1.548088145111132,"pointY":0.4210402603661751}},"layers":[{"animations":[{"timeOffset":0,"beginTime":1e-100,"repeatCount":0,"animations":[{"timeOffset":0,"from":{"scalar":0},"beginTime":0,"repeatCount":0,"fillMode":"both","duration":0.5,"autoreverses":false,"timingFunction":"EaseInEaseOut","property":"opacity","to":{"scalar":1}},{"timeOffset":0,"from":{"scalar":false},"beginTime":0,"repeatCount":0,"fillMode":"forwards","property":"hidden","autoreverses":false,"duration":0.5,"to":{"scalar":false}}],"fillMode":"both","autoreverses":false,"duration":0.5}],"layers":[],"texturedRectangle":{"singleTextureOpacity":1,"textXHeight":0,"shapePath":{"lineWidth":1,"flatness":0.6,"lineCapStyle":0,"elements":[{"type":"MoveToPoint","points":[[2.261456467541564,43.86234591123434]]},{"type":"AddLine","points":[[43.63717005369045,2.486632325085452]]},{"type":"AddLine","points":[[84.63093473729248,43.48039700868753]]},{"type":"AddLine","points":[[43.25522115114359,84.85611059483642]]},{"type":"CloseSubpath"},{"type":"MoveToPoint","points":[[2.261456467541564,43.86234591123434]]}],"windingRule":0,"lineJoinStyle":0,"miterLimit":10},"isBackgroundTexture":true,"textBaseline":0,"isVerticalText":false,"textureType":5},"initialState":{"affineTransform":[1,0,0,1,0,0],"masksToBounds":false,"rotation":0,"scale":1,"position":{"pointX":42.29920370423827,"pointY":42.07402784669438},"width":87,"sublayerTransform":[1,0,0,0,0,1,0,0,0,0,1,0,0,0,0,1],"contentsRect":{"y":0,"x":0,"width":1,"height":1},"opacity":1,"edgeAntialiasingMask":0,"height":87,"hidden":true,"anchorPoint":{"pointX":0.5,"pointY":0.5}},"texture":"28BEA62E24033B5528476B7B1872C063"}]}]},"effects":[],"duration":0.5,"type":"buildIn","attributes":{"direction":11},"name":"apple:wipe","objectID":"EC17F182-85EA-4087-B397-F13CA2D275A2"},{"beginTime":0,"baseLayer":{"animations":[],"initialState":{"affineTransform":[1,0,0,1,0,0],"masksToBounds":false,"rotation":0,"scale":1,"position":{"pointX":480.0000381469727,"pointY":344.2496490478516},"width":895.9654541015625,"sublayerTransform":[1,0,0,0,0,1,0,0,0,0,1,0,0,0,0,1],"contentsRect":{"y":0,"x":0,"width":1,"height":1},"opacity":1,"edgeAntialiasingMask":251658240,"height":197.3597717285156,"hidden":false,"anchorPoint":{"pointX":0.5,"pointY":0.5}},"objectID":"C97B1760-B315-4A7F-B2FF-A24D7251502C","layers":[{"animations":[],"initialState":{"affineTransform":[1,0,0,1,0,0],"masksToBounds":false,"rotation":0,"scale":1,"position":{"pointX":447.9826889038086,"pointY":24.43023681640625},"width":895.9654541015625,"sublayerTransform":[1,0,0,0,0,1,0,0,0,0,1,-0.0007001582493355197,0,0,0,1],"contentsRect":{"y":0,"x":0,"width":1,"height":1},"opacity":1,"edgeAntialiasingMask":251658240,"height":197.3597717285156,"hidden":false,"anchorPoint":{"pointX":0.4999999574236122,"pointY":0.1237852912092542}},"layers":[{"animations":[{"timeOffset":0,"beginTime":1e-100,"repeatCount":0,"animations":[{"timeOffset":0,"from":{"scalar":0},"beginTime":0,"repeatCount":0,"fillMode":"both","duration":0.5,"autoreverses":false,"timingFunction":"EaseInEaseOut","property":"opacity","to":{"scalar":1}},{"timeOffset":0,"from":{"scalar":false},"beginTime":0,"repeatCount":0,"fillMode":"forwards","property":"hidden","autoreverses":false,"duration":0.5,"to":{"scalar":false}}],"fillMode":"both","autoreverses":false,"duration":0.5}],"layers":[],"texturedRectangle":{"isBackgroundTexture":true,"singleTextureOpacity":1,"textureType":5,"textBaseline":0,"textXHeight":0,"isVerticalText":false},"initialState":{"affineTransform":[1,0,0,1,0,0],"masksToBounds":false,"rotation":0,"scale":1,"position":{"pointX":471.4826889038086,"pointY":91.43023681640625},"width":785,"sublayerTransform":[1,0,0,0,0,1,0,0,0,0,1,0,0,0,0,1],"contentsRect":{"y":0,"x":0,"width":1,"height":1},"opacity":1,"edgeAntialiasingMask":0,"height":186,"hidden":true,"anchorPoint":{"pointX":0.5,"pointY":0.5}},"texture":"BA5196ECBF181D644F02D7CA74EA7770"}]}]},"effects":[],"duration":0.5,"type":"buildIn","attributes":{"direction":11},"name":"apple:wipe","objectID":"C97B1760-B315-4A7F-B2FF-A24D7251502C"},{"beginTime":0,"baseLayer":{"animations":[],"initialState":{"affineTransform":[1,0,0,1,0,0],"masksToBounds":false,"rotation":0,"scale":1,"position":{"pointX":479.9999980926514,"pointY":395.1772766113281},"width":84.49079861331063,"sublayerTransform":[1,0,0,0,0,1,0,0,0,0,1,0,0,0,0,1],"contentsRect":{"y":0,"x":0,"width":1,"height":1},"opacity":1,"edgeAntialiasingMask":251658240,"height":84.49079861331063,"hidden":false,"anchorPoint":{"pointX":0.5,"pointY":0.5}},"objectID":"4B639911-3A01-40C0-840B-84EE77E0BE38","layers":[{"animations":[],"initialState":{"affineTransform":[1,0,0,1,0,0],"masksToBounds":false,"rotation":0,"scale":1,"position":{"pointX":42.24540121400389,"pointY":-82.93187730467281},"width":84.49079861331063,"sublayerTransform":[1,0,0,0,0,1,0,0,0,0,1,-0.0007001582493355197,0,0,0,1],"contentsRect":{"y":0,"x":0,"width":1,"height":1},"opacity":1,"edgeAntialiasingMask":251658240,"height":84.49079861331063,"hidden":false,"anchorPoint":{"pointX":0.5000000225746307,"pointY":-0.9815492179713847}},"layers":[{"animations":[{"timeOffset":0,"beginTime":1e-100,"repeatCount":0,"animations":[{"timeOffset":0,"from":{"scalar":0},"beginTime":0,"repeatCount":0,"fillMode":"both","duration":0.5,"autoreverses":false,"timingFunction":"EaseInEaseOut","property":"opacity","to":{"scalar":1}},{"timeOffset":0,"from":{"scalar":false},"beginTime":0,"repeatCount":0,"fillMode":"forwards","property":"hidden","autoreverses":false,"duration":0.5,"to":{"scalar":false}}],"fillMode":"both","autoreverses":false,"duration":0.5}],"layers":[],"texturedRectangle":{"singleTextureOpacity":1,"textXHeight":0,"shapePath":{"lineWidth":1,"flatness":0.6,"lineCapStyle":0,"elements":[{"type":"MoveToPoint","points":[[2.815258957775939,44.36825106260153]]},{"type":"AddLine","points":[[44.19097254392483,2.99253747645264]]},{"type":"AddLine","points":[[85.18473722752685,43.98630216005472]]},{"type":"AddLine","points":[[43.80902364137796,85.36201574620361]]},{"type":"CloseSubpath"},{"type":"MoveToPoint","points":[[2.815258957775939,44.36825106260153]]}],"windingRule":0,"lineJoinStyle":0,"miterLimit":10},"isBackgroundTexture":true,"textBaseline":0,"isVerticalText":false,"textureType":5},"initialState":{"affineTransform":[1,0,0,1,0,0],"masksToBounds":false,"rotation":0,"scale":1,"position":{"pointX":42.24540121400389,"pointY":42.06812269532719},"width":88,"sublayerTransform":[1,0,0,0,0,1,0,0,0,0,1,0,0,0,0,1],"contentsRect":{"y":0,"x":0,"width":1,"height":1},"opacity":1,"edgeAntialiasingMask":0,"height":88,"hidden":true,"anchorPoint":{"pointX":0.5,"pointY":0.5}},"texture":"D1C3167F6F8B15101F23012D177C21C4"}]}]},"effects":[],"duration":0.5,"type":"buildIn","attributes":{"direction":11},"name":"apple:wipe","objectID":"4B639911-3A01-40C0-840B-84EE77E0BE38"},{"beginTime":0,"baseLayer":{"animations":[],"initialState":{"affineTransform":[1,0,0,1,0,0],"masksToBounds":false,"rotation":0,"scale":1,"position":{"pointX":566.092374801636,"pointY":276.6713714599609},"width":84.49079861331063,"sublayerTransform":[1,0,0,0,0,1,0,0,0,0,1,0,0,0,0,1],"contentsRect":{"y":0,"x":0,"width":1,"height":1},"opacity":1,"edgeAntialiasingMask":251658240,"height":84.49079861331063,"hidden":false,"anchorPoint":{"pointX":0.5,"pointY":0.5}},"objectID":"6003E3F1-B5C9-4381-909F-6B8413F12354","layers":[{"animations":[],"initialState":{"affineTransform":[1,0,0,1,0,0],"masksToBounds":false,"rotation":0,"scale":1,"position":{"pointX":-43.8469754949806,"pointY":35.57402784669438},"width":84.49079861331063,"sublayerTransform":[1,0,0,0,0,1,0,0,0,0,1,-0.0007001582493355197,0,0,0,1],"contentsRect":{"y":0,"x":0,"width":1,"height":1},"opacity":1,"edgeAntialiasingMask":251658240,"height":84.49079861331063,"hidden":false,"anchorPoint":{"pointX":-0.5189556284780219,"pointY":0.4210402603661751}},"layers":[{"animations":[{"timeOffset":0,"beginTime":1e-100,"repeatCount":0,"animations":[{"timeOffset":0,"from":{"scalar":0},"beginTime":0,"repeatCount":0,"fillMode":"both","duration":0.5,"autoreverses":false,"timingFunction":"EaseInEaseOut","property":"opacity","to":{"scalar":1}},{"timeOffset":0,"from":{"scalar":false},"beginTime":0,"repeatCount":0,"fillMode":"forwards","property":"hidden","autoreverses":false,"duration":0.5,"to":{"scalar":false}}],"fillMode":"both","autoreverses":false,"duration":0.5}],"layers":[],"texturedRectangle":{"singleTextureOpacity":1,"textXHeight":0,"shapePath":{"lineWidth":1,"flatness":0.6,"lineCapStyle":0,"elements":[{"type":"MoveToPoint","points":[[2.90763566676037,43.86234591123434]]},{"type":"AddLine","points":[[44.28334925290926,2.486632325085452]]},{"type":"AddLine","points":[[85.27711393651134,43.48039700868753]]},{"type":"AddLine","points":[[43.90140035036245,84.85611059483642]]},{"type":"CloseSubpath"},{"type":"MoveToPoint","points":[[2.90763566676037,43.86234591123434]]}],"windingRule":0,"lineJoinStyle":0,"miterLimit":10},"isBackgroundTexture":true,"textBaseline":0,"isVerticalText":false,"textureType":5},"initialState":{"affineTransform":[1,0,0,1,0,0],"masksToBounds":false,"rotation":0,"scale":1,"position":{"pointX":42.1530245050194,"pointY":42.07402784669438},"width":88,"sublayerTransform":[1,0,0,0,0,1,0,0,0,0,1,0,0,0,0,1],"contentsRect":{"y":0,"x":0,"width":1,"height":1},"opacity":1,"edgeAntialiasingMask":0,"height":87,"hidden":true,"anchorPoint":{"pointX":0.5,"pointY":0.5}},"texture":"CA4490732041C7B0251B62D01F9E94E8"}]}]},"effects":[],"duration":0.5,"type":"buildIn","attributes":{"direction":11},"name":"apple:wipe","objectID":"6003E3F1-B5C9-4381-909F-6B8413F12354"}],"automaticPlay":true,"hyperlinks":[],"accessibility":[{"text":"Q&A","targetRectangle":{"y":384.7321557998657,"x":540.3806519508362,"width":42.236328125,"height":24}},{"text":"1","targetRectangle":{"y":249.1697637121404,"x":377.3387699127197,"width":28.125,"height":56}},{"text":"3","targetRectangle":{"y":368.7321626226628,"x":464.9229984283447,"width":28.125,"height":56}},{"text":"前端简史","targetRectangle":{"y":263.1697630882263,"x":248.3153595924377,"width":80,"height":28}},{"text":"2","targetRectangle":{"y":249.1697637121404,"x":552.2708988189697,"width":28.125,"height":56}},{"text":"常见技术介绍","targetRectangle":{"y":263.1697630882263,"x":630.1360014947832,"width":120,"height":28}}],"baseLayer":{"animations":[],"initialState":{"affineTransform":[1,0,0,1,0,0],"masksToBounds":false,"rotation":0,"scale":1,"position":{"pointX":480,"pointY":270},"width":960,"sublayerTransform":[1,0,0,0,0,1,0,0,0,0,1,0,0,0,0,1],"contentsRect":{"y":0,"x":0,"width":1,"height":1},"opacity":1,"edgeAntialiasingMask":251658240,"height":540,"hidden":false,"anchorPoint":{"pointX":0.5,"pointY":0.5}},"layers":[{"animations":[],"initialState":{"affineTransform":[1,0,0,1,0,0],"masksToBounds":false,"rotation":0,"scale":1,"position":{"pointX":480,"pointY":270},"width":960,"sublayerTransform":[1,0,0,0,0,1,0,0,0,0,1,0,0,0,0,1],"contentsRect":{"y":0,"x":0,"width":1,"height":1},"opacity":1,"edgeAntialiasingMask":251658240,"height":540,"hidden":false,"anchorPoint":{"pointX":0.5,"pointY":0.5}},"layers":[{"animations":[],"initialState":{"affineTransform":[1,0,0,1,0,0],"masksToBounds":false,"rotation":0,"scale":1,"position":{"pointX":480,"pointY":270},"width":960,"sublayerTransform":[1,0,0,0,0,1,0,0,0,0,1,0,0,0,0,1],"contentsRect":{"y":0,"x":0,"width":1,"height":1},"opacity":1,"edgeAntialiasingMask":251658240,"height":540,"hidden":false,"anchorPoint":{"pointX":0.5,"pointY":0.5}},"layers":[{"animations":[],"layers":[],"texturedRectangle":{"isBackgroundTexture":true,"singleTextureOpacity":1,"textureType":1,"textBaseline":0,"textXHeight":0,"isVerticalText":false},"initialState":{"affineTransform":[1,0,0,1,0,0],"masksToBounds":false,"rotation":0,"scale":1,"position":{"pointX":480,"pointY":270},"width":960,"sublayerTransform":[1,0,0,0,0,1,0,0,0,0,1,0,0,0,0,1],"contentsRect":{"y":0,"x":0,"width":1,"height":1},"opacity":1,"edgeAntialiasingMask":0,"height":540,"hidden":false,"anchorPoint":{"pointX":0.5,"pointY":0.5}},"texture":"8090B41B8C80976C270CD97E8301335F"}]}]},{"animations":[],"initialState":{"affineTransform":[1,0,0,1,0,0],"masksToBounds":false,"rotation":0,"scale":1,"position":{"pointX":480,"pointY":270},"width":960,"sublayerTransform":[1,0,0,0,0,1,0,0,0,0,1,0,0,0,0,1],"contentsRect":{"y":0,"x":0,"width":1,"height":1},"opacity":1,"edgeAntialiasingMask":251658240,"height":540,"hidden":false,"anchorPoint":{"pointX":0.5,"pointY":0.5}},"layers":[{"animations":[],"initialState":{"affineTransform":[1,0,0,1,0,0],"masksToBounds":false,"rotation":0,"scale":1,"position":{"pointX":479.9999542236328,"pointY":153.3014946574592},"width":352.1852722167969,"sublayerTransform":[1,0,0,0,0,1,0,0,0,0,1,0,0,0,0,1],"contentsRect":{"y":0,"x":0,"width":1,"height":1},"opacity":1,"edgeAntialiasingMask":251658240,"height":47.37007915866843,"hidden":false,"anchorPoint":{"pointX":0.5,"pointY":0.5}},"objectID":"E7C0F144-AD3B-4153-9F82-968386AE8923","layers":[{"animations":[],"layers":[],"texturedRectangle":{"singleTextureOpacity":1,"textXHeight":0.5600000000000001,"textBaseline":0.8260491689046224,"isBackgroundTexture":true,"isVerticalText":false,"textColor":[1,1,1,1],"textureType":6},"initialState":{"affineTransform":[1,0,0,1,0,0],"masksToBounds":false,"rotation":0,"scale":1,"position":{"pointX":60.09268188476562,"pointY":24.383544921875},"width":112,"sublayerTransform":[1,0,0,0,0,1,0,0,0,0,1,0,0,0,0,1],"contentsRect":{"y":0,"x":0,"width":1,"height":1},"opacity":1,"edgeAntialiasingMask":0,"height":30,"hidden":true,"anchorPoint":{"pointX":0.5,"pointY":0.5}},"texture":"789EB8E7F504F944BCAF5FB827FDCF95"}]}]},{"animations":[],"initialState":{"affineTransform":[1,0,0,1,0,0],"masksToBounds":false,"rotation":0,"scale":1,"position":{"pointX":480,"pointY":270},"width":960,"sublayerTransform":[1,0,0,0,0,1,0,0,0,0,1,0,0,0,0,1],"contentsRect":{"y":0,"x":0,"width":1,"height":1},"opacity":1,"edgeAntialiasingMask":251658240,"height":540,"hidden":false,"anchorPoint":{"pointX":0.5,"pointY":0.5}},"layers":[{"animations":[],"initialState":{"affineTransform":[1,0,0,1,0,0],"masksToBounds":false,"rotation":0,"scale":1,"position":{"pointX":391.446195602417,"pointY":276.6713714599609},"width":84.49079861331063,"sublayerTransform":[1,0,0,0,0,1,0,0,0,0,1,0,0,0,0,1],"contentsRect":{"y":0,"x":0,"width":1,"height":1},"opacity":1,"edgeAntialiasingMask":251658240,"height":84.49079861331063,"hidden":false,"anchorPoint":{"pointX":0.5,"pointY":0.5}},"objectID":"EC17F182-85EA-4087-B397-F13CA2D275A2","layers":[{"animations":[],"layers":[],"texturedRectangle":{"singleTextureOpacity":1,"textXHeight":0,"shapePath":{"lineWidth":1,"flatness":0.6,"lineCapStyle":0,"elements":[{"type":"MoveToPoint","points":[[2.261456467541564,43.86234591123434]]},{"type":"AddLine","points":[[43.63717005369045,2.486632325085452]]},{"type":"AddLine","points":[[84.63093473729248,43.48039700868753]]},{"type":"AddLine","points":[[43.25522115114359,84.85611059483642]]},{"type":"CloseSubpath"},{"type":"MoveToPoint","points":[[2.261456467541564,43.86234591123434]]}],"windingRule":0,"lineJoinStyle":0,"miterLimit":10},"isBackgroundTexture":true,"textBaseline":0,"isVerticalText":false,"textureType":5},"initialState":{"affineTransform":[1,0,0,1,0,0],"masksToBounds":false,"rotation":0,"scale":1,"position":{"pointX":42.29920370423827,"pointY":42.07402784669438},"width":87,"sublayerTransform":[1,0,0,0,0,1,0,0,0,0,1,0,0,0,0,1],"contentsRect":{"y":0,"x":0,"width":1,"height":1},"opacity":1,"edgeAntialiasingMask":0,"height":87,"hidden":true,"anchorPoint":{"pointX":0.5,"pointY":0.5}},"texture":"28BEA62E24033B5528476B7B1872C063"}]}]},{"animations":[],"initialState":{"affineTransform":[1,0,0,1,0,0],"masksToBounds":false,"rotation":0,"scale":1,"position":{"pointX":480,"pointY":270},"width":960,"sublayerTransform":[1,0,0,0,0,1,0,0,0,0,1,0,0,0,0,1],"contentsRect":{"y":0,"x":0,"width":1,"height":1},"opacity":1,"edgeAntialiasingMask":251658240,"height":540,"hidden":false,"anchorPoint":{"pointX":0.5,"pointY":0.5}},"layers":[{"animations":[],"initialState":{"affineTransform":[1,0,0,1,0,0],"masksToBounds":false,"rotation":0,"scale":1,"position":{"pointX":480.0000381469727,"pointY":344.2496490478516},"width":895.9654541015625,"sublayerTransform":[1,0,0,0,0,1,0,0,0,0,1,0,0,0,0,1],"contentsRect":{"y":0,"x":0,"width":1,"height":1},"opacity":1,"edgeAntialiasingMask":251658240,"height":197.3597717285156,"hidden":false,"anchorPoint":{"pointX":0.5,"pointY":0.5}},"objectID":"C97B1760-B315-4A7F-B2FF-A24D7251502C","layers":[{"animations":[],"layers":[],"texturedRectangle":{"isBackgroundTexture":true,"singleTextureOpacity":1,"textureType":5,"textBaseline":0,"textXHeight":0,"isVerticalText":false},"initialState":{"affineTransform":[1,0,0,1,0,0],"masksToBounds":false,"rotation":0,"scale":1,"position":{"pointX":471.4826889038086,"pointY":91.43023681640625},"width":785,"sublayerTransform":[1,0,0,0,0,1,0,0,0,0,1,0,0,0,0,1],"contentsRect":{"y":0,"x":0,"width":1,"height":1},"opacity":1,"edgeAntialiasingMask":0,"height":186,"hidden":true,"anchorPoint":{"pointX":0.5,"pointY":0.5}},"texture":"BA5196ECBF181D644F02D7CA74EA7770"}]}]},{"animations":[],"initialState":{"affineTransform":[1,0,0,1,0,0],"masksToBounds":false,"rotation":0,"scale":1,"position":{"pointX":480,"pointY":270},"width":960,"sublayerTransform":[1,0,0,0,0,1,0,0,0,0,1,0,0,0,0,1],"contentsRect":{"y":0,"x":0,"width":1,"height":1},"opacity":1,"edgeAntialiasingMask":251658240,"height":540,"hidden":false,"anchorPoint":{"pointX":0.5,"pointY":0.5}},"layers":[{"animations":[],"initialState":{"affineTransform":[1,0,0,1,0,0],"masksToBounds":false,"rotation":0,"scale":1,"position":{"pointX":479.9999980926514,"pointY":395.1772766113281},"width":84.49079861331063,"sublayerTransform":[1,0,0,0,0,1,0,0,0,0,1,0,0,0,0,1],"contentsRect":{"y":0,"x":0,"width":1,"height":1},"opacity":1,"edgeAntialiasingMask":251658240,"height":84.49079861331063,"hidden":false,"anchorPoint":{"pointX":0.5,"pointY":0.5}},"objectID":"4B639911-3A01-40C0-840B-84EE77E0BE38","layers":[{"animations":[],"layers":[],"texturedRectangle":{"singleTextureOpacity":1,"textXHeight":0,"shapePath":{"lineWidth":1,"flatness":0.6,"lineCapStyle":0,"elements":[{"type":"MoveToPoint","points":[[2.815258957775939,44.36825106260153]]},{"type":"AddLine","points":[[44.19097254392483,2.99253747645264]]},{"type":"AddLine","points":[[85.18473722752685,43.98630216005472]]},{"type":"AddLine","points":[[43.80902364137796,85.36201574620361]]},{"type":"CloseSubpath"},{"type":"MoveToPoint","points":[[2.815258957775939,44.36825106260153]]}],"windingRule":0,"lineJoinStyle":0,"miterLimit":10},"isBackgroundTexture":true,"textBaseline":0,"isVerticalText":false,"textureType":5},"initialState":{"affineTransform":[1,0,0,1,0,0],"masksToBounds":false,"rotation":0,"scale":1,"position":{"pointX":42.24540121400389,"pointY":42.06812269532719},"width":88,"sublayerTransform":[1,0,0,0,0,1,0,0,0,0,1,0,0,0,0,1],"contentsRect":{"y":0,"x":0,"width":1,"height":1},"opacity":1,"edgeAntialiasingMask":0,"height":88,"hidden":true,"anchorPoint":{"pointX":0.5,"pointY":0.5}},"texture":"D1C3167F6F8B15101F23012D177C21C4"}]}]},{"animations":[],"initialState":{"affineTransform":[1,0,0,1,0,0],"masksToBounds":false,"rotation":0,"scale":1,"position":{"pointX":480,"pointY":270},"width":960,"sublayerTransform":[1,0,0,0,0,1,0,0,0,0,1,0,0,0,0,1],"contentsRect":{"y":0,"x":0,"width":1,"height":1},"opacity":1,"edgeAntialiasingMask":251658240,"height":540,"hidden":false,"anchorPoint":{"pointX":0.5,"pointY":0.5}},"layers":[{"animations":[],"initialState":{"affineTransform":[1,0,0,1,0,0],"masksToBounds":false,"rotation":0,"scale":1,"position":{"pointX":566.092374801636,"pointY":276.6713714599609},"width":84.49079861331063,"sublayerTransform":[1,0,0,0,0,1,0,0,0,0,1,0,0,0,0,1],"contentsRect":{"y":0,"x":0,"width":1,"height":1},"opacity":1,"edgeAntialiasingMask":251658240,"height":84.49079861331063,"hidden":false,"anchorPoint":{"pointX":0.5,"pointY":0.5}},"objectID":"6003E3F1-B5C9-4381-909F-6B8413F12354","layers":[{"animations":[],"layers":[],"texturedRectangle":{"singleTextureOpacity":1,"textXHeight":0,"shapePath":{"lineWidth":1,"flatness":0.6,"lineCapStyle":0,"elements":[{"type":"MoveToPoint","points":[[2.90763566676037,43.86234591123434]]},{"type":"AddLine","points":[[44.28334925290926,2.486632325085452]]},{"type":"AddLine","points":[[85.27711393651134,43.48039700868753]]},{"type":"AddLine","points":[[43.90140035036245,84.85611059483642]]},{"type":"CloseSubpath"},{"type":"MoveToPoint","points":[[2.90763566676037,43.86234591123434]]}],"windingRule":0,"lineJoinStyle":0,"miterLimit":10},"isBackgroundTexture":true,"textBaseline":0,"isVerticalText":false,"textureType":5},"initialState":{"affineTransform":[1,0,0,1,0,0],"masksToBounds":false,"rotation":0,"scale":1,"position":{"pointX":42.1530245050194,"pointY":42.07402784669438},"width":88,"sublayerTransform":[1,0,0,0,0,1,0,0,0,0,1,0,0,0,0,1],"contentsRect":{"y":0,"x":0,"width":1,"height":1},"opacity":1,"edgeAntialiasingMask":0,"height":87,"hidden":true,"anchorPoint":{"pointX":0.5,"pointY":0.5}},"texture":"CA4490732041C7B0251B62D01F9E94E8"}]}]}]}},{"effects":[{"beginTime":0,"baseLayer":{"animations":[],"initialState":{"affineTransform":[1,0,0,1,0,0],"masksToBounds":false,"rotation":0,"scale":1,"position":{"pointX":480,"pointY":270},"width":960,"sublayerTransform":[1,0,0,0,0,1,0,0,0,0,1,0,0,0,0,1],"contentsRect":{"y":0,"x":0,"width":1,"height":1},"opacity":1,"edgeAntialiasingMask":251658240,"height":540,"hidden":false,"anchorPoint":{"pointX":0.5,"pointY":0.5}},"objectID":"0","layers":[{"animations":[],"initialState":{"affineTransform":[1,0,0,1,0,0],"masksToBounds":false,"rotation":0,"scale":1,"position":{"pointX":480,"pointY":270},"width":960,"sublayerTransform":[1,0,0,0,0,1,0,0,0,0,1,-0.0007001582493355197,0,0,0,1],"contentsRect":{"y":0,"x":0,"width":1,"height":1},"opacity":1,"edgeAntialiasingMask":251658240,"height":540,"hidden":false,"anchorPoint":{"pointX":0.5,"pointY":0.5}},"layers":[{"animations":[{"timeOffset":0,"beginTime":0,"repeatCount":0,"animations":[{"timeOffset":0,"from":{"scalar":0.5},"beginTime":0,"repeatCount":0,"fillMode":"both","duration":0.1800000071525574,"autoreverses":false,"timingFunction":"EaseOut","property":"opacity","to":{"scalar":1}},{"timeOffset":0,"from":{"scalar":false},"beginTime":0,"repeatCount":0,"fillMode":"removed","property":"doubleSided","autoreverses":false,"duration":1.200000047683716,"to":{"scalar":false}},{"repeatCount":0,"timingControlPoint2y":1,"from":{"scalar":1.570796326794897},"timingFunction":"custom","timeOffset":0,"autoreverses":false,"timingControlPoint1x":0.5004994869232178,"fillMode":"removed","property":"transform.rotation.y","duration":1.200000047683716,"beginTime":0,"timingControlPoint2x":0.4667648673057556,"timingControlPoint1y":0,"to":{"scalar":-0}},{"timeOffset":0,"values":[{"scalar":-480},{"scalar":-482.7122375107719},{"scalar":-491.4963694389104},{"scalar":-507.4216649766908},{"scalar":-531.4814278080248},{"scalar":-563.9354002130623},{"scalar":-602.8931341446789},{"scalar":-642.2664473872533},{"scalar":-671.0952691883798},{"scalar":-678.1918808765924},{"scalar":-660.8910884319104},{"scalar":-627.2562051028073},{"scalar":-588.7207890773366},{"scalar":-553.3733213820864},{"scalar":-524.8462828429995},{"scalar":-503.9107550684525},{"scalar":-490.0542555334095},{"scalar":-482.3806518171581},{"scalar":-480}],"beginTime":0,"repeatCount":0,"fillMode":"both","property":"transform.translation.z","autoreverses":false,"duration":1.200000047683716,"keyTimes":[0,0.05555555555555555,0.1111111111111111,0.1666666666666667,0.2222222222222222,0.2777777777777778,0.3333333333333333,0.3888888888888889,0.4444444444444444,0.5,0.5555555555555556,0.6111111111111112,0.6666666666666666,0.7222222222222222,0.7777777777777778,0.8333333333333334,0.8888888888888888,0.9444444444444444,1]},{"timeOffset":0,"from":{"scalar":-480},"beginTime":0,"repeatCount":0,"fillMode":"removed","property":"anchorPointZ","autoreverses":false,"duration":1.200000047683716,"to":{"scalar":-480}}],"fillMode":"both","autoreverses":false,"duration":1.200000047683716}],"layers":[],"texturedRectangle":{"isBackgroundTexture":false,"singleTextureOpacity":1,"textureType":0,"textBaseline":0,"textXHeight":0,"isVerticalText":false},"initialState":{"affineTransform":[1,0,0,1,0,0],"masksToBounds":false,"rotation":0,"scale":1,"position":{"pointX":480,"pointY":270},"width":960,"sublayerTransform":[1,0,0,0,0,1,0,0,0,0,1,0,0,0,0,1],"contentsRect":{"y":0,"x":0,"width":1,"height":1},"opacity":1,"edgeAntialiasingMask":0,"height":540,"hidden":false,"anchorPoint":{"pointX":0.5,"pointY":0.5}},"texture":"D9D638C947AE8DEEB09674AFD582DF6A"},{"animations":[{"timeOffset":0,"beginTime":0,"repeatCount":0,"animations":[{"timeOffset":0,"from":{"scalar":1},"beginTime":0,"repeatCount":0,"fillMode":"both","duration":1.200000047683716,"autoreverses":false,"timingFunction":"EaseIn","property":"opacity","to":{"scalar":0}},{"timeOffset":0,"from":{"scalar":false},"beginTime":0,"repeatCount":0,"fillMode":"removed","property":"doubleSided","autoreverses":false,"duration":1.200000047683716,"to":{"scalar":false}},{"repeatCount":0,"timingControlPoint2y":1,"from":{"scalar":-0},"timingFunction":"custom","timeOffset":0,"autoreverses":false,"timingControlPoint1x":0.5004994869232178,"fillMode":"removed","property":"transform.rotation.y","duration":1.200000047683716,"beginTime":0,"timingControlPoint2x":0.4667648673057556,"timingControlPoint1y":0,"to":{"scalar":-1.570796326794897}},{"timeOffset":0,"values":[{"scalar":-480},{"scalar":-482.7122375107719},{"scalar":-491.4963694389108},{"scalar":-507.4216649766908},{"scalar":-531.4814278080248},{"scalar":-563.9354002130623},{"scalar":-602.8931341446789},{"scalar":-642.2664473872535},{"scalar":-671.0952691883798},{"scalar":-678.1918808765924},{"scalar":-660.8910884319105},{"scalar":-627.2562051028074},{"scalar":-588.7207890773366},{"scalar":-553.3733213820866},{"scalar":-524.8462828429995},{"scalar":-503.9107550684527},{"scalar":-490.0542555334093},{"scalar":-482.3806518171581},{"scalar":-480}],"beginTime":0,"repeatCount":0,"fillMode":"both","property":"transform.translation.z","autoreverses":false,"duration":1.200000047683716,"keyTimes":[0,0.05555555555555555,0.1111111111111111,0.1666666666666667,0.2222222222222222,0.2777777777777778,0.3333333333333333,0.3888888888888889,0.4444444444444444,0.5,0.5555555555555556,0.6111111111111112,0.6666666666666666,0.7222222222222222,0.7777777777777778,0.8333333333333334,0.8888888888888888,0.9444444444444444,1]},{"timeOffset":0,"from":{"scalar":-480},"beginTime":0,"repeatCount":0,"fillMode":"removed","property":"anchorPointZ","autoreverses":false,"duration":1.200000047683716,"to":{"scalar":-480}}],"fillMode":"both","autoreverses":false,"duration":1.200000047683716}],"layers":[],"texturedRectangle":{"isBackgroundTexture":false,"singleTextureOpacity":1,"textureType":0,"textBaseline":0,"textXHeight":0,"isVerticalText":false},"initialState":{"affineTransform":[1,0,0,1,0,0],"masksToBounds":false,"rotation":0,"scale":1,"position":{"pointX":480,"pointY":270},"width":960,"sublayerTransform":[1,0,0,0,0,1,0,0,0,0,1,0,0,0,0,1],"contentsRect":{"y":0,"x":0,"width":1,"height":1},"opacity":1,"edgeAntialiasingMask":0,"height":540,"hidden":false,"anchorPoint":{"pointX":0.5,"pointY":0.5}},"texture":"85BCA963944A71E6E88951D92BFE7D94"}]}]},"effects":[],"duration":1.200000047683716,"type":"transition","name":"apple:3D-cube","objectID":"0"}],"automaticPlay":false,"hyperlinks":[],"accessibility":[{"text":"Q&A","targetRectangle":{"y":384.7321557998657,"x":540.3806519508362,"width":42.236328125,"height":24}},{"text":"内容概述","targetRectangle":{"y":133.3014943599701,"x":307.5923573970795,"width":112,"height":40}},{"text":"1","targetRectangle":{"y":249.1697637121404,"x":377.3387699127197,"width":28.125,"height":56}},{"text":"3","targetRectangle":{"y":368.7321626226628,"x":464.9229984283447,"width":28.125,"height":56}},{"text":"前端简史","targetRectangle":{"y":263.1697630882263,"x":248.3153595924377,"width":80,"height":28}},{"text":"2","targetRectangle":{"y":249.1697637121404,"x":552.2708988189697,"width":28.125,"height":56}},{"text":"常见技术介绍","targetRectangle":{"y":263.1697630882263,"x":630.1360014947832,"width":120,"height":28}}],"baseLayer":{"animations":[],"initialState":{"affineTransform":[1,0,0,1,0,0],"masksToBounds":false,"rotation":0,"scale":1,"position":{"pointX":480,"pointY":270},"width":960,"sublayerTransform":[1,0,0,0,0,1,0,0,0,0,1,0,0,0,0,1],"contentsRect":{"y":0,"x":0,"width":1,"height":1},"opacity":1,"edgeAntialiasingMask":251658240,"height":540,"hidden":false,"anchorPoint":{"pointX":0.5,"pointY":0.5}},"objectID":"0","layers":[{"animations":[],"initialState":{"affineTransform":[1,0,0,1,0,0],"masksToBounds":false,"rotation":0,"scale":1,"position":{"pointX":480,"pointY":270},"width":960,"sublayerTransform":[1,0,0,0,0,1,0,0,0,0,1,-0.0007001582493355197,0,0,0,1],"contentsRect":{"y":0,"x":0,"width":1,"height":1},"opacity":1,"edgeAntialiasingMask":251658240,"height":540,"hidden":false,"anchorPoint":{"pointX":0.5,"pointY":0.5}},"layers":[{"animations":[],"layers":[],"texturedRectangle":{"isBackgroundTexture":false,"singleTextureOpacity":1,"textureType":0,"textBaseline":0,"textXHeight":0,"isVerticalText":false},"initialState":{"affineTransform":[1,0,0,1,0,0],"masksToBounds":false,"rotation":0,"scale":1,"position":{"pointX":480,"pointY":270},"width":960,"sublayerTransform":[1,0,0,0,0,1,0,0,0,0,1,0,0,0,0,1],"contentsRect":{"y":0,"x":0,"width":1,"height":1},"opacity":1,"edgeAntialiasingMask":0,"height":540,"hidden":false,"anchorPoint":{"pointX":0.5,"pointY":0.5}},"texture":"85BCA963944A71E6E88951D92BFE7D94"}]}]}}]}